configconverter/__init__.py
configconverter/cli.py
configconverter/converter.py
configconverter/emitters.py
configconverter/exceptions.py
configconverter/parsers.py
configconverter/utils.py
configconverter-0.3.0.dist-info/LICENSE
configconverter-0.3.0.dist-info/METADATA
configconverter-0.3.0.dist-info/WHEEL
configconverter-0.3.0.dist-info/entry_points.txt
configconverter-0.3.0.dist-info/RECORD
