Metadata-Version: 2.1
Name: configconverter
Version: 0.3.0
Summary: A versatile tool to convert configuration files between different formats.
Home-page: https://github.com/ankitaglawe/configconverter
License: MIT
Keywords: configuration,converter,json,yaml,toml,ini,xml
Author: Ankit Aglawe
Author-email: aglawe.ankit@gmail.com
Requires-Python: >=3.8,<4.0
Classifier: Development Status :: 4 - Beta
Classifier: Intended Audience :: Developers
Classifier: License :: OSI Approved :: MIT License
Classifier: Operating System :: OS Independent
Classifier: Programming Language :: Python :: 3
Classifier: Programming Language :: Python :: 3.8
Classifier: Programming Language :: Python :: 3.9
Classifier: Programming Language :: Python :: 3.10
Classifier: Programming Language :: Python :: 3.11
Classifier: Programming Language :: Python :: 3.12
Classifier: Topic :: Software Development :: Libraries
Classifier: Topic :: Utilities
Requires-Dist: PyYAML (>=6.0,<7.0)
Requires-Dist: dicttoxml (>=1.7.16,<2.0.0)
Requires-Dist: toml (>=0.10.2,<0.11.0)
Requires-Dist: xmltodict (>=0.14.0,<0.15.0)
Project-URL: Documentation, https://configconverter.readthedocs.io
Project-URL: Repository, https://github.com/ankitaglawe/configconverter
